confit2canard/__init__.py
confit2canard/__main__.py
confit2canard/config.py
confit2canard/node.py
confit2canard/vault.py
confit2canard-0.1.1.dist-info/LICENSE.txt
confit2canard-0.1.1.dist-info/METADATA
confit2canard-0.1.1.dist-info/WHEEL
confit2canard-0.1.1.dist-info/RECORD
