Metadata-Version: 2.1
Name: confit2canard
Version: 0.1.1
Summary: Minimalistic configuration library with encryption and a tasty name
License: MIT
Keywords: configuration
Author: Benjamin Hirschfield
Author-email: benjamin.hirschfield@dolead.com
Maintainer: Benjamin Hirschfield
Maintainer-email: benjamin.hirschfield@dolead.com
Requires-Python: >=3.9,<4.0
Classifier: License :: OSI Approved :: MIT License
Classifier: Programming Language :: Python :: 3
Classifier: Programming Language :: Python :: 3.9
Classifier: Programming Language :: Python :: 3.10
Classifier: Programming Language :: Python :: 3.11
Classifier: Programming Language :: Python :: 3.12
Classifier: Programming Language :: Python :: 3.13
Requires-Dist: pycryptodome (>=3.21.0,<4.0.0)
Requires-Dist: pyyaml (>=6.0.2,<7.0.0)
